gray_code_converter/gray_code_unit.sv
module gray_code_unit #(
    parameter int WIDTH = 4
) (
    input logic [WIDTH-1:0] binary_in,
    output logic [WIDTH-1:0] gray_out,

    input logic [WIDTH-1:0] gray_in,
    output logic [WIDTH-1:0] binary_out
);

// convert binary to gray code
assign gray_out = binary_in ^ (binary_in >> 1);

//convert gray to binary
always_comb begin
    binary_out[WIDTH-1] = gray_in[WIDTH-1];
    for (int i = WIDTH-2; i >= 0; i--) begin
        binary_out[i] = gray_in[i] ^ binary_out[i+1];
    end
end

endmodule

gray_code_converter/gray_code_unit_tb.sv
`timescale 1ns/1ps

module tb_gray_code_unit;

    localparam int WIDTH = 4;

    // Interface Signals
    logic [WIDTH-1:0] binary_in;
    logic [WIDTH-1:0] gray_out;
    
    logic [WIDTH-1:0] gray_in;
    logic [WIDTH-1:0] binary_out;

    // Instantiate Device Under Test (DUT)
    gray_code_unit #(
        .WIDTH(WIDTH)
    ) dut (
        .binary_in (binary_in),
        .gray_out  (gray_out),
        .gray_in   (gray_in),
        .binary_out(binary_out)
    );

    initial begin
        $dumpfile("waves.vcd");
        $dumpvars(0, tb_gray_code_unit);
    end

    // Track test status
    int error_count = 0;

    initial begin
        $display("\n--- Starting Gray Code Unit Self-Checking Testbench ---");

        // Directed Test Loop: Iterate through all valid 4-bit values
        for (int i = 0; i < (1 << WIDTH); i++) begin
            
            // 1. Test Binary-to-Gray
            binary_in = i[WIDTH-1:0];
            #10; // Allow combinational propagation
            
            // Single bit-flip check relative to previous value
            if (i > 0) begin
                logic [WIDTH-1:0] prev_gray, gray_diff;
                prev_gray = (i - 1) ^ ((i - 1) >> 1);
                gray_diff = gray_out ^ prev_gray;

                // $onehot checks if exactly 1 bit transitioned
                if (!$onehot(gray_diff)) begin
                    $error("[FAIL] Multi-bit transition! Bin: %0d | Prev Gray: %b | Curr Gray: %b", 
                           i, prev_gray, gray_out);
                    error_count++;
                end
            end

            // 2. Test Roundtrip (Gray-to-Binary)
            gray_in = gray_out;
            #10; // Allow combinational propagation

            if (binary_out !== binary_in) begin
                $error("[FAIL] Roundtrip mismatch! Expected Bin: %b | Got: %b (Gray: %b)", 
                       binary_in, binary_out, gray_in);
                error_count++;
            end else begin
                $display("[PASS] Bin: %b (%2d) --> Gray: %b --> Recon Bin: %b", 
                         binary_in, binary_in, gray_out, binary_out);
            end
        end

        // Final Report
        $display("-----------------------------------------------------");
        if (error_count == 0) begin
            $display("SUCCESS: All tests passed with 0 errors.");
        end else begin
            $display("FAILURE: Completed with %0d error(s).", error_count);
        end
        $display("-----------------------------------------------------\n");
        $finish;
    end

endmodule

gray_code_converter/waves.vcd
$date
	Fri Sep 18 09:04:29 2026
$end
$version
	Icarus Verilog
$end
$timescale
	1ps
$end
$scope module tb_gray_code_unit $end
$var wire 4 ! gray_out [3:0] $end
$var wire 4 " binary_out [3:0] $end
$var parameter 32 # WIDTH $end
$var reg 4 $ binary_in [3:0] $end
$var reg 4 % gray_in [3:0] $end
$var integer 32 & error_count [31:0] $end
$scope module dut $end
$var wire 4 ' binary_in [3:0] $end
$var wire 4 ( gray_in [3:0] $end
$var wire 4 ) gray_out [3:0] $end
$var parameter 32 * WIDTH $end
$var reg 4 + binary_out [3:0] $end
$scope begin $ivl_for_loop1 $end
$var integer 32 , i [31:0] $end
$upscope $end
$upscope $end
$scope begin $ivl_for_loop0 $end
$var integer 32 - i [31:0] $end
$scope begin $unm_blk_4 $end
$var reg 4 . gray_diff [3:0] $end
$var reg 4 / prev_gray [3:0] $end
$upscope $end
$upscope $end
$upscope $end
$enddefinitions $end
$comment Show the parameter values. $end
$dumpall
b100 *
b100 #
$end
#0
$dumpvars
bx /
bx .
b0 -
b11111111111111111111111111111111 ,
bx +
b0 )
bx (
b0 '
b0 &
bx %
b0 $
bx "
b0 !
$end
#10000
b11111111111111111111111111111111 ,
b0 "
b0 +
b0 %
b0 (
#20000
b1 !
b1 )
b1 $
b1 '
b1 -
#30000
b1 "
b1 +
b11111111111111111111111111111111 ,
b1 %
b1 (
b1 .
b0 /
#40000
b11 !
b11 )
b10 $
b10 '
b10 -
#50000
b10 "
b10 +
b11111111111111111111111111111111 ,
b11 %
b11 (
b10 .
b1 /
#60000
b10 !
b10 )
b11 $
b11 '
b11 -
#70000
b11 "
b11 +
b11111111111111111111111111111111 ,
b10 %
b10 (
b1 .
b11 /
#80000
b110 !
b110 )
b100 $
b100 '
b100 -
#90000
b100 "
b100 +
b11111111111111111111111111111111 ,
b110 %
b110 (
b100 .
b10 /
#100000
b111 !
b111 )
b101 $
b101 '
b101 -
#110000
b101 "
b101 +
b11111111111111111111111111111111 ,
b111 %
b111 (
b1 .
b110 /
#120000
b101 !
b101 )
b110 $
b110 '
b110 -
#130000
b110 "
b110 +
b11111111111111111111111111111111 ,
b101 %
b101 (
b10 .
b111 /
#140000
b100 !
b100 )
b111 $
b111 '
b111 -
#150000
b111 "
b111 +
b11111111111111111111111111111111 ,
b100 %
b100 (
b1 .
b101 /
#160000
b1100 !
b1100 )
b1000 $
b1000 '
b1000 -
#170000
b11111111111111111111111111111111 ,
b1000 "
b1000 +
b1100 %
b1100 (
b1000 .
b100 /
#180000
b1101 !
b1101 )
b1001 $
b1001 '
b1001 -
#190000
b1001 "
b1001 +
b11111111111111111111111111111111 ,
b1101 %
b1101 (
b1 .
b1100 /
#200000
b1111 !
b1111 )
b1010 $
b1010 '
b1010 -
#210000
b1010 "
b1010 +
b11111111111111111111111111111111 ,
b1111 %
b1111 (
b10 .
b1101 /
#220000
b1110 !
b1110 )
b1011 $
b1011 '
b1011 -
#230000
b1011 "
b1011 +
b11111111111111111111111111111111 ,
b1110 %
b1110 (
b1 .
b1111 /
#240000
b1010 !
b1010 )
b1100 $
b1100 '
b1100 -
#250000
b1100 "
b1100 +
b11111111111111111111111111111111 ,
b1010 %
b1010 (
b100 .
b1110 /
#260000
b1011 !
b1011 )
b1101 $
b1101 '
b1101 -
#270000
b1101 "
b1101 +
b11111111111111111111111111111111 ,
b1011 %
b1011 (
b1 .
b1010 /
#280000
b1001 !
b1001 )
b1110 $
b1110 '
b1110 -
#290000
b1110 "
b1110 +
b11111111111111111111111111111111 ,
b1001 %
b1001 (
b10 .
b1011 /
#300000
b1000 !
b1000 )
b1111 $
b1111 '
b1111 -
#310000
b1111 "
b1111 +
b11111111111111111111111111111111 ,
b1000 %
b1000 (
b1 .
b1001 /
#320000
b10000 -
